edopi/__init__.py
edopi/domain/__init__.py
edopi/domain/balzano_diagram.py
edopi/domain/chroma.py
edopi/domain/gcycle.py
edopi/domain/scale.py
edopi/domain/tonal_system.py
edopi/domain/utils.py
edopi-1.1.0.dist-info/LICENSE.txt
edopi-1.1.0.dist-info/METADATA
edopi-1.1.0.dist-info/WHEEL
edopi-1.1.0.dist-info/top_level.txt
edopi-1.1.0.dist-info/RECORD
