Metadata-Version: 2.1
Name: edopi
Version: 1.1.0
Summary: Python package to deal with Group-Theoretic microtonal music structures
Home-page: https://github.com/luansimoes/edopi
Author: Flavia Elias e Luan Simões
Author-email: luansimoes@cos.ufrj.br
License: MIT License
Keywords: microtonal edo music group-theoretic
License-File: LICENSE.txt
Requires-Dist: numpy
Requires-Dist: matplotlib
